Metadata-Version: 2.1
Name: Oge-distributions
Version: 0.1
Summary: Gaussian and Binomial distributions
